bibsane.py
BibSane-0.1.3.dist-info/COPYING
BibSane-0.1.3.dist-info/METADATA
BibSane-0.1.3.dist-info/WHEEL
BibSane-0.1.3.dist-info/entry_points.txt
BibSane-0.1.3.dist-info/top_level.txt
BibSane-0.1.3.dist-info/RECORD
