Metadata-Version: 2.1
Name: BibSane
Version: 0.1.3
Summary: Sanitize BibTeX files without going insane
Author-email: Toon Verstraelen <toon.verstraelen@ugent.be>
License: GNU GENERAL PUBLIC LICENSE
Project-URL: Issues, https://github.com/reproducible-reporting/bibsane/issues
Project-URL: Source, https://github.com/reproducible-reporting/bibsane/
Project-URL: Changelog, https://github.com/reproducible-reporting/bibsane/blob/main/CHANGELOG.md
Classifier: Development Status :: 3 - Alpha
Classifier: Environment :: Console
Classifier: Intended Audience :: Science/Research
Classifier: Intended Audience :: Education
Classifier: License :: OSI Approved :: GNU General Public License v3 or later (GPLv3+)
Classifier: Natural Language :: English
Classifier: Operating System :: POSIX
Classifier: Operating System :: MacOS
Classifier: Programming Language :: Python :: 3
Classifier: Topic :: Text Processing :: Markup :: LaTeX
Requires-Python: >=3.10
License-File: COPYING
Requires-Dist: bibtexparser
Requires-Dist: PyYAML
Requires-Dist: attrs
Requires-Dist: cattrs
